labelseg/__init__.py
labelseg/app.py
labelseg/app_dialog.py
labelseg/dialog.py
labelseg/imgLabel.py
labelseg/imgs_rc.py
labelseg/mainwindow.py
labelseg/util.py
labelseg/icons/color.png
labelseg/icons/edit.png
labelseg/icons/ellipse.png
labelseg/icons/open.png
labelseg/icons/polygon.png
labelseg/icons/rectangle.png
labelseg/icons/save.png
labelseg/icons/undo.png
labelseg/icons/zoom-in.png
labelseg/icons/zoom-out.png
labelseg-0.0.4.dist-info/METADATA
labelseg-0.0.4.dist-info/RECORD
labelseg-0.0.4.dist-info/WHEEL
labelseg-0.0.4.dist-info/entry_points.txt
labelseg-0.0.4.dist-info/top_level.txt
